{
  "ok": true,
  "generated_at": "2026-03-03T18:09:06.762Z",
  "run_date": "2026-03-03",
  "dry_run": false,
  "source": "priority_repo_major_update_daily",
  "bootstrap_managed_repos": [
    {
      "target": "quantfusion",
      "managed_repo": {
        "action": "updated",
        "id": "29c2e09a-dc84-4ff0-bc51-3f3dc1886e17",
        "client_name": "quantfusion"
      }
    },
    {
      "target": "payclaw",
      "managed_repo": {
        "action": "updated",
        "id": "d763be9a-6990-4fd3-92d9-b32290210653",
        "client_name": "PayClaw"
      }
    },
    {
      "target": "cookiespass",
      "managed_repo": {
        "action": "updated",
        "id": "aa15123c-93d3-4123-8c9b-7f0622ec0508",
        "client_name": "CookiesPass"
      }
    },
    {
      "target": "cookiespass_copy",
      "managed_repo": {
        "action": "updated",
        "id": "ada9101d-1ac7-4e5f-9863-af4001ceee97",
        "client_name": "TempeCookiesPass"
      }
    },
    {
      "target": "clawpay",
      "managed_repo": {
        "action": "updated",
        "id": "9a2633af-e30c-4e43-aaa9-52d69a8c39d8",
        "client_name": "ClawPay"
      }
    }
  ],
  "targets": [
    {
      "key": "payclaw",
      "repo": "local/payclaw",
      "skipped": "already_queued_today"
    },
    {
      "key": "quantfusion",
      "repo": "local/quantfusion",
      "skipped": "already_queued_today"
    },
    {
      "key": "cookiespass",
      "repo": "local/CookiesPass",
      "skipped": "already_queued_today"
    },
    {
      "key": "tempecookiespass",
      "repo": "local/TempeCookiesPass",
      "skipped": "already_queued_today"
    },
    {
      "key": "clawpay",
      "repo": "local/clawpay",
      "priority": 10,
      "high_priority_lane": true,
      "repo_metrics_72h": {
        "failure_count": 0,
        "completed_count": 0
      },
      "task": {
        "created": true,
        "id": "8ccb878d-0ba1-4709-82d7-ba0166361180",
        "type": "opencode_controller",
        "priority": 10,
        "idempotencyKey": "opencode_controller:c2ca33c51f0a8de18e5db981f4cb50a47bc7eb923bac6b9f77abd25f815774e8"
      }
    },
    {
      "key": "robloxgitsync",
      "repo": "local/RobloxGitSync",
      "skipped": "already_queued_today"
    },
    {
      "key": "claw_architect",
      "repo": "local/claw-architect",
      "priority": 6,
      "high_priority_lane": false,
      "repo_metrics_72h": {
        "failure_count": 0,
        "completed_count": 1039
      },
      "task": {
        "created": true,
        "id": "49b45d52-3e43-4d40-afb8-a193b4e61982",
        "type": "opencode_controller",
        "priority": 6,
        "idempotencyKey": "opencode_controller:b02d446acf179344461311a861f1ee6d64414466da1dd2b53baca454bdf58fae"
      }
    },
    {
      "key": "inbound_cookies",
      "repo": "local/Inbound-cookies",
      "priority": 6,
      "high_priority_lane": false,
      "repo_metrics_72h": {
        "failure_count": 0,
        "completed_count": 130
      },
      "task": {
        "created": true,
        "id": "3598fc30-27ea-4d99-b64c-624f3358fc53",
        "type": "opencode_controller",
        "priority": 6,
        "idempotencyKey": "opencode_controller:0f4028864f48c1514c2ab9953651bd2c3da03503e639f47fb79155ff7a5c41c5"
      }
    },
    {
      "key": "manychatdupe",
      "repo": "local/manychatdupe",
      "priority": 6,
      "high_priority_lane": false,
      "repo_metrics_72h": {
        "failure_count": 0,
        "completed_count": 130
      },
      "task": {
        "created": true,
        "id": "8b7fb452-8d91-4311-88f8-618ac7db00d0",
        "type": "opencode_controller",
        "priority": 6,
        "idempotencyKey": "opencode_controller:73f37e4d32d28f539f65e62a69a73995435e8ddaa0721a7bbc5bbd07599b6b05"
      }
    },
    {
      "key": "pdfezfill",
      "repo": "local/PdfEzFill",
      "priority": 6,
      "high_priority_lane": false,
      "repo_metrics_72h": {
        "failure_count": 0,
        "completed_count": 130
      },
      "task": {
        "created": true,
        "id": "2ba69736-d6f3-450c-9f1f-86602195611d",
        "type": "opencode_controller",
        "priority": 6,
        "idempotencyKey": "opencode_controller:2a8ead6891623eb63f4379464b9d2b87fd7e985074b989655e06453886c48afd"
      }
    },
    {
      "key": "blackwallstreetopoly",
      "repo": "local/BlackWallStreetopoly",
      "skipped": "already_queued_today"
    },
    {
      "key": "3dgamestake2",
      "repo": "local/3dgamestake2",
      "priority": 6,
      "high_priority_lane": false,
      "repo_metrics_72h": {
        "failure_count": 0,
        "completed_count": 128
      },
      "task": {
        "created": false,
        "reason": "duplicate_active",
        "type": "opencode_controller",
        "idempotencyKey": "opencode_controller:0b5606ec423f84f78c3be0980353f999fcf662e056f7a7e3b86597ea6930f3de"
      }
    },
    {
      "key": "gbusupdate",
      "repo": "local/gbusupdate",
      "priority": 6,
      "high_priority_lane": false,
      "repo_metrics_72h": {
        "failure_count": 0,
        "completed_count": 128
      },
      "task": {
        "created": false,
        "reason": "duplicate_active",
        "type": "opencode_controller",
        "idempotencyKey": "opencode_controller:7edbd818cb628062ffebd4657e8b382c11c8b1197243b8d56f8a370d462b469c"
      }
    },
    {
      "key": "gocrawdaddy",
      "repo": "local/GoCrawdaddy",
      "priority": 6,
      "high_priority_lane": false,
      "repo_metrics_72h": {
        "failure_count": 0,
        "completed_count": 128
      },
      "task": {
        "created": true,
        "id": "9e3f22f6-9730-495a-8071-a6b7a9704e76",
        "type": "opencode_controller",
        "priority": 6,
        "idempotencyKey": "opencode_controller:9c765cf020d4835b1bb9471881a352cf487f546440c510eaa5d98978cadce360"
      }
    },
    {
      "key": "leadgengit",
      "repo": "local/leadgengit",
      "priority": 6,
      "high_priority_lane": false,
      "repo_metrics_72h": {
        "failure_count": 0,
        "completed_count": 128
      },
      "task": {
        "created": false,
        "reason": "duplicate_active",
        "type": "opencode_controller",
        "idempotencyKey": "opencode_controller:ecfc7382f087cb6243447a1fff195f114a7c4e2e0a415d084c4b90cbd4dd466e"
      }
    },
    {
      "key": "booked",
      "repo": "local/booked",
      "priority": 6,
      "high_priority_lane": false,
      "repo_metrics_72h": {
        "failure_count": 0,
        "completed_count": 127
      },
      "task": {
        "created": false,
        "reason": "duplicate_active",
        "type": "opencode_controller",
        "idempotencyKey": "opencode_controller:fc5279be2b92ea3e2f8901ce060451123f0b0b55fc49a3fe9f488ef5d24792e7"
      }
    },
    {
      "key": "captureinbound",
      "repo": "local/CaptureInbound",
      "priority": 6,
      "high_priority_lane": false,
      "repo_metrics_72h": {
        "failure_count": 0,
        "completed_count": 127
      },
      "task": {
        "created": true,
        "id": "8e8edc69-bc84-4d43-b3c1-999554c0d32c",
        "type": "opencode_controller",
        "priority": 6,
        "idempotencyKey": "opencode_controller:b884b1d38a028d6b694c7f226bd61ee2f1bd99cf5a2e4b2c79d4a9bd092fc67c"
      }
    },
    {
      "key": "glitch_app",
      "repo": "local/glitch-app",
      "priority": 6,
      "high_priority_lane": false,
      "repo_metrics_72h": {
        "failure_count": 0,
        "completed_count": 127
      },
      "task": {
        "created": true,
        "id": "fa7eabba-21e1-4ac5-8f27-9338935fc5eb",
        "type": "opencode_controller",
        "priority": 6,
        "idempotencyKey": "opencode_controller:62e2cb83892980ec23d241d1d9203c3c5e1697a96fbe0321b4d7b23fba6ebca8"
      }
    },
    {
      "key": "patentpal",
      "repo": "local/PatentPal",
      "priority": 6,
      "high_priority_lane": false,
      "repo_metrics_72h": {
        "failure_count": 0,
        "completed_count": 127
      },
      "task": {
        "created": true,
        "id": "f1a9b965-42c3-492c-8429-c02b00415711",
        "type": "opencode_controller",
        "priority": 6,
        "idempotencyKey": "opencode_controller:5829bfa7361a0a6aa8f206eb4052d8a4caee62fc69c1d33f342c1dc72ac61743"
      }
    },
    {
      "key": "nfcverify",
      "repo": "local/nfcverify",
      "priority": 6,
      "high_priority_lane": false,
      "repo_metrics_72h": {
        "failure_count": 0,
        "completed_count": 126
      },
      "task": {
        "created": true,
        "id": "005d3402-4e5b-4b38-ac24-f0064cfb6437",
        "type": "opencode_controller",
        "priority": 6,
        "idempotencyKey": "opencode_controller:c2443933e5a7c396c7fc2be72acfb49e04c7dcde11c39f1508a2b5eebd474c56"
      }
    },
    {
      "key": "pingmyself",
      "repo": "local/pingmyself",
      "priority": 6,
      "high_priority_lane": false,
      "repo_metrics_72h": {
        "failure_count": 0,
        "completed_count": 126
      },
      "task": {
        "created": true,
        "id": "e05999be-ec53-40c6-8996-307b52074087",
        "type": "opencode_controller",
        "priority": 6,
        "idempotencyKey": "opencode_controller:9b11da398044a518e2dc7a4a74b55d5c3b34ea2256ff2553a7511575d106cd81"
      }
    },
    {
      "key": "capture",
      "repo": "local/capture",
      "priority": 6,
      "high_priority_lane": false,
      "repo_metrics_72h": {
        "failure_count": 0,
        "completed_count": 125
      },
      "task": {
        "created": true,
        "id": "cfe9b1de-5554-40e5-a9d5-32b3bf9d576d",
        "type": "opencode_controller",
        "priority": 6,
        "idempotencyKey": "opencode_controller:e3aebab627bbff3906ef9dfee877361f9dcec4ebb6d5830ad6bfec6d30ea6bcc"
      }
    },
    {
      "key": "3dgameartacademy",
      "repo": "local/3DGameArtAcademy",
      "priority": 6,
      "high_priority_lane": false,
      "repo_metrics_72h": {
        "failure_count": 0,
        "completed_count": 124
      },
      "task": {
        "created": true,
        "id": "19733115-59a7-47f5-9f58-a386bfcd6aed",
        "type": "opencode_controller",
        "priority": 6,
        "idempotencyKey": "opencode_controller:5fcd17a526b863bea133e648aad2ae797531653ba00b51dcf6bff4e6e1097fc1"
      }
    },
    {
      "key": "baktokingcom",
      "repo": "local/BakTokingcom",
      "priority": 6,
      "high_priority_lane": false,
      "repo_metrics_72h": {
        "failure_count": 0,
        "completed_count": 124
      },
      "task": {
        "created": true,
        "id": "11fe8710-1d2c-4f88-a543-365e12028877",
        "type": "opencode_controller",
        "priority": 6,
        "idempotencyKey": "opencode_controller:15ea922f52dbef5f85c373d83faab7a5e50479b7b3d259cf69749c845ae0e5ff"
      }
    },
    {
      "key": "coinstbl",
      "repo": "local/Coinstbl",
      "priority": 6,
      "high_priority_lane": false,
      "repo_metrics_72h": {
        "failure_count": 0,
        "completed_count": 124
      },
      "task": {
        "created": false,
        "reason": "duplicate_active",
        "type": "opencode_controller",
        "idempotencyKey": "opencode_controller:d26a9b62f35b913c716dad0e5f891cb5119d3aab54ea53b4dcd12e0f15e9cc8c"
      }
    },
    {
      "key": "leadgen",
      "repo": "local/Leadgen",
      "priority": 6,
      "high_priority_lane": false,
      "repo_metrics_72h": {
        "failure_count": 0,
        "completed_count": 124
      },
      "task": {
        "created": true,
        "id": "0c444570-eab8-4ed2-9134-e2bc6adca468",
        "type": "opencode_controller",
        "priority": 6,
        "idempotencyKey": "opencode_controller:3bd8143a99694fc68fccaad982b1cfad54c2a31ee27b63710799f8e985815649"
      }
    },
    {
      "key": "madirectory",
      "repo": "local/Madirectory",
      "priority": 6,
      "high_priority_lane": false,
      "repo_metrics_72h": {
        "failure_count": 0,
        "completed_count": 124
      },
      "task": {
        "created": true,
        "id": "354723ac-4b85-4681-8cad-b8c1e7580650",
        "type": "opencode_controller",
        "priority": 6,
        "idempotencyKey": "opencode_controller:92ed7064961416dbe57a004e39361a8acd79dd4c8adc5c61a6c0acfc53063fdf"
      }
    },
    {
      "key": "mediatranscribepro",
      "repo": "local/MediaTranscribePro",
      "priority": 6,
      "high_priority_lane": false,
      "repo_metrics_72h": {
        "failure_count": 0,
        "completed_count": 124
      },
      "task": {
        "created": true,
        "id": "48287a06-a59e-4e5d-a197-da951db831ef",
        "type": "opencode_controller",
        "priority": 6,
        "idempotencyKey": "opencode_controller:3554a960e4bffd8ff03fbed477debe4b42f90596a795cd11c917f55858bb87be"
      }
    },
    {
      "key": "autopay_ui",
      "repo": "local/autopay_ui",
      "priority": 6,
      "high_priority_lane": false,
      "repo_metrics_72h": {
        "failure_count": 0,
        "completed_count": 123
      },
      "task": {
        "created": true,
        "id": "930aed74-eb85-45d5-9003-aab5d6f2a832",
        "type": "opencode_controller",
        "priority": 6,
        "idempotencyKey": "opencode_controller:12d32ab398544929079c9fcf90c90759bfdaf4a9720e86f16114063c065a7ab5"
      }
    },
    {
      "key": "cookies_pass",
      "repo": "local/Cookies_Pass",
      "priority": 6,
      "high_priority_lane": false,
      "repo_metrics_72h": {
        "failure_count": 0,
        "completed_count": 123
      },
      "task": {
        "created": true,
        "id": "eef5ea59-ecaa-40d2-bb45-d07112af5b31",
        "type": "opencode_controller",
        "priority": 6,
        "idempotencyKey": "opencode_controller:349b8748f9f2e7e637d3750acacfcc702e019a741ba783552f30dd3c0e9a708b"
      }
    },
    {
      "key": "leadgen3",
      "repo": "local/LeadGen3",
      "priority": 6,
      "high_priority_lane": false,
      "repo_metrics_72h": {
        "failure_count": 0,
        "completed_count": 123
      },
      "task": {
        "created": true,
        "id": "8b074a1c-8c97-4f3f-8ab4-c8d5e0464004",
        "type": "opencode_controller",
        "priority": 6,
        "idempotencyKey": "opencode_controller:12a5b257844f885af56dfaf6dcf69fb15ed652d47d7366f85e83a23f22a6bb61"
      }
    },
    {
      "key": "foodtruckpass",
      "repo": "local/FoodTruckPass",
      "priority": 6,
      "high_priority_lane": false,
      "repo_metrics_72h": {
        "failure_count": 0,
        "completed_count": 122
      },
      "task": {
        "created": true,
        "id": "ca91e45f-0360-4c64-9123-cc531c76a356",
        "type": "opencode_controller",
        "priority": 6,
        "idempotencyKey": "opencode_controller:ff26d7273abeaa0be7d57158647a5d381a7a4c6c4e1edd37f773b5b433f70afa"
      }
    },
    {
      "key": "infinitedata",
      "repo": "local/infinitedata",
      "priority": 6,
      "high_priority_lane": false,
      "repo_metrics_72h": {
        "failure_count": 0,
        "completed_count": 122
      },
      "task": {
        "created": true,
        "id": "cf318e50-65f5-4668-badd-87b538f2372d",
        "type": "opencode_controller",
        "priority": 6,
        "idempotencyKey": "opencode_controller:299532fcc181289d194916b9653ea4c0975b1d028458fefdefaf7fab1460083d"
      }
    },
    {
      "key": "howtowatchstream_smartkb",
      "repo": "local/HowtoWatchStream-SmartKB",
      "priority": 6,
      "high_priority_lane": false,
      "repo_metrics_72h": {
        "failure_count": 0,
        "completed_count": 121
      },
      "task": {
        "created": true,
        "id": "706251d3-1d7d-4b5b-b429-50d8c74b3eb6",
        "type": "opencode_controller",
        "priority": 6,
        "idempotencyKey": "opencode_controller:488a04de290530f3aa64fc2745b6b5b47137dc39175af5d30679a9af3651de79"
      }
    },
    {
      "key": "coinstbl",
      "repo": "local/CoinStbl",
      "priority": 6,
      "high_priority_lane": false,
      "repo_metrics_72h": {
        "failure_count": 0,
        "completed_count": 120
      },
      "task": {
        "created": true,
        "id": "5e9315ff-e834-46bf-af47-3ef2428cf3b1",
        "type": "opencode_controller",
        "priority": 6,
        "idempotencyKey": "opencode_controller:3313ad489c7897d2f9020f42c8a4000f5a72e68f2b90bbeefdac03527218b0b7"
      }
    },
    {
      "key": "cookies_tempe",
      "repo": "local/cookies-tempe",
      "priority": 6,
      "high_priority_lane": false,
      "repo_metrics_72h": {
        "failure_count": 0,
        "completed_count": 120
      },
      "task": {
        "created": true,
        "id": "34f4a754-b3f2-440e-aeb0-93d6f968da53",
        "type": "opencode_controller",
        "priority": 6,
        "idempotencyKey": "opencode_controller:a8103257cc033f8c918c2e6aeb1a4da7ef88509954f6295fae509f0ba4c91310"
      }
    },
    {
      "key": "crave",
      "repo": "local/crave",
      "priority": 6,
      "high_priority_lane": false,
      "repo_metrics_72h": {
        "failure_count": 0,
        "completed_count": 120
      },
      "task": {
        "created": true,
        "id": "f2a6b7ae-0f88-4e5e-914f-abd7d6790038",
        "type": "opencode_controller",
        "priority": 6,
        "idempotencyKey": "opencode_controller:be4801112b1d2b0852aa2571a1503452d9d43d328eb5eedf91addaf4e2069012"
      }
    },
    {
      "key": "mytutor",
      "repo": "local/mytutor",
      "priority": 6,
      "high_priority_lane": false,
      "repo_metrics_72h": {
        "failure_count": 0,
        "completed_count": 120
      },
      "task": {
        "created": true,
        "id": "180cd12f-1b29-454f-bfd1-b890b2da3a96",
        "type": "opencode_controller",
        "priority": 6,
        "idempotencyKey": "opencode_controller:f11a80e8904ec94b8dd7439830b6486f1da6f0dff8ac996549b4592eaf38610d"
      }
    },
    {
      "key": "patentpal",
      "repo": "local/patentpal",
      "priority": 6,
      "high_priority_lane": false,
      "repo_metrics_72h": {
        "failure_count": 0,
        "completed_count": 120
      },
      "task": {
        "created": false,
        "reason": "duplicate_active",
        "type": "opencode_controller",
        "idempotencyKey": "opencode_controller:5180c25e12eca1a16f42000a923adc27361c19584a29d9578c762506dec12e36"
      }
    },
    {
      "key": "leadgenai",
      "repo": "local/LeadGenAi",
      "priority": 6,
      "high_priority_lane": false,
      "repo_metrics_72h": {
        "failure_count": 0,
        "completed_count": 118
      },
      "task": {
        "created": true,
        "id": "c796f1aa-eb00-4bee-a2d4-dbb3db3a3477",
        "type": "opencode_controller",
        "priority": 6,
        "idempotencyKey": "opencode_controller:3761a916f569c37c042ce51b4cbef94c40a4bb77c130ee21bf3d0d8f2c8008dd"
      }
    },
    {
      "key": "3ddesignafterschool",
      "repo": "local/3ddesignafterschool",
      "priority": 6,
      "high_priority_lane": false,
      "repo_metrics_72h": {
        "failure_count": 0,
        "completed_count": 113
      },
      "task": {
        "created": true,
        "id": "cf89c6bf-8113-41fb-a61d-14eaad414e45",
        "type": "opencode_controller",
        "priority": 6,
        "idempotencyKey": "opencode_controller:b97aaab1c4b89d1195ffc870d96e2bf2fac6d86d94d1b2b15bbd299816d9759e"
      }
    },
    {
      "key": "pingmyself",
      "repo": "local/PingMyself",
      "priority": 6,
      "high_priority_lane": false,
      "repo_metrics_72h": {
        "failure_count": 0,
        "completed_count": 107
      },
      "task": {
        "created": true,
        "id": "856d0788-f56e-47b7-a090-8278eca5d3e0",
        "type": "opencode_controller",
        "priority": 6,
        "idempotencyKey": "opencode_controller:982d86c8186d7a276417dcde7030a1bae1b9f15f6cc5ced72d719499bd1cc545"
      }
    },
    {
      "key": "v0_morningops",
      "repo": "local/v0-morningops",
      "priority": 6,
      "high_priority_lane": false,
      "repo_metrics_72h": {
        "failure_count": 0,
        "completed_count": 12
      },
      "task": {
        "created": true,
        "id": "b715b394-d019-4836-a484-263076291d30",
        "type": "opencode_controller",
        "priority": 6,
        "idempotencyKey": "opencode_controller:8f7c343f6cf2178cd54d9e7c1c465bf7e21c27a34a2695ef92dddeddf8d5da8d"
      }
    },
    {
      "key": "veritap",
      "repo": "local/veritap",
      "priority": 6,
      "high_priority_lane": false,
      "repo_metrics_72h": {
        "failure_count": 0,
        "completed_count": 12
      },
      "task": {
        "created": true,
        "id": "521667d0-6457-4e96-9024-fdb331e7f51e",
        "type": "opencode_controller",
        "priority": 6,
        "idempotencyKey": "opencode_controller:5508bdd00cb50ac7af46fa5ea9cccc9a3b5e0c6a408e6b4ec0df1d6c88711e90"
      }
    },
    {
      "key": "qarunner",
      "repo": "local/QARunner",
      "priority": 6,
      "high_priority_lane": false,
      "repo_metrics_72h": {
        "failure_count": 0,
        "completed_count": 0
      },
      "task": {
        "created": true,
        "id": "1d63a5d1-17df-41a3-b282-bf3e94841c96",
        "type": "opencode_controller",
        "priority": 6,
        "idempotencyKey": "opencode_controller:12ae8c00e1a323eacb3a89b6ce40bd4baf4ba0b3d35d8a36e0459a6502bda5e8"
      }
    },
    {
      "key": "reframed",
      "repo": "local/reframed",
      "priority": 6,
      "high_priority_lane": false,
      "repo_metrics_72h": {
        "failure_count": 0,
        "completed_count": 0
      },
      "task": {
        "created": true,
        "id": "091250dc-3740-451e-a4d2-8689f403534e",
        "type": "opencode_controller",
        "priority": 6,
        "idempotencyKey": "opencode_controller:0b68b4393686609a91103248661c9c6a7f9221559fadd37293673f8bf9669888"
      }
    },
    {
      "key": "smartkb",
      "repo": "local/SmartKB",
      "priority": 6,
      "high_priority_lane": false,
      "repo_metrics_72h": {
        "failure_count": 0,
        "completed_count": 0
      },
      "task": {
        "created": true,
        "id": "f63b1b00-8a8e-48ca-bcaa-a0935ea5a4c8",
        "type": "opencode_controller",
        "priority": 6,
        "idempotencyKey": "opencode_controller:0218e492dc9fcda28f77d78f36c17b5a5081d5a9b92f718636acedf1bf7c0d05"
      }
    },
    {
      "key": "socialaipilot",
      "repo": "local/SocialAiPilot",
      "priority": 6,
      "high_priority_lane": false,
      "repo_metrics_72h": {
        "failure_count": 0,
        "completed_count": 0
      },
      "task": {
        "created": true,
        "id": "9fff09cb-12f3-42ab-b347-c6844804de14",
        "type": "opencode_controller",
        "priority": 6,
        "idempotencyKey": "opencode_controller:a6e79e9249ea7c9139afc52fb8c3e4e8f31ba88b5c336fe25df32e3578ea0c53"
      }
    },
    {
      "key": "somaveachaser",
      "repo": "local/SomaveaChaser",
      "priority": 6,
      "high_priority_lane": false,
      "repo_metrics_72h": {
        "failure_count": 0,
        "completed_count": 0
      },
      "task": {
        "created": true,
        "id": "73d02110-e8d4-4291-8f56-080f1eeeeeef",
        "type": "opencode_controller",
        "priority": 6,
        "idempotencyKey": "opencode_controller:c123ea488878b9d06842314b1a9d2f28c9d840be48d52e9930e3b20ea19dc6a3"
      }
    },
    {
      "key": "syrup_client_line_sheet",
      "repo": "local/syrup-client-line-sheet",
      "priority": 6,
      "high_priority_lane": false,
      "repo_metrics_72h": {
        "failure_count": 0,
        "completed_count": 0
      },
      "task": {
        "created": true,
        "id": "5cc67e1f-3dde-4fd1-8cc9-b59ce8f133b8",
        "type": "opencode_controller",
        "priority": 6,
        "idempotencyKey": "opencode_controller:9cde873a37cc2c8fe7d7d4c21ac3f73d414529e0e691a3ae0b1d7283a019d4bd"
      }
    },
    {
      "key": "syrup_internal_line_sheet",
      "repo": "local/syrup-internal-line-sheet",
      "priority": 6,
      "high_priority_lane": false,
      "repo_metrics_72h": {
        "failure_count": 0,
        "completed_count": 0
      },
      "task": {
        "created": true,
        "id": "43ab8e24-97c5-4b85-b612-abe59c52966c",
        "type": "opencode_controller",
        "priority": 6,
        "idempotencyKey": "opencode_controller:d312840f9deeb1ac5cfb2edabd350e65aea0127530b9a32cb68dc8960a3b7bc6"
      }
    },
    {
      "key": "tap2",
      "repo": "local/tap2",
      "priority": 6,
      "high_priority_lane": false,
      "repo_metrics_72h": {
        "failure_count": 0,
        "completed_count": 0
      },
      "task": {
        "created": true,
        "id": "fe372c76-9708-4578-bf44-87b9fa47645d",
        "type": "opencode_controller",
        "priority": 6,
        "idempotencyKey": "opencode_controller:107fb851e66ad216b14f30c2470f45697412e397ccbd8f461675d3a0fad771af"
      }
    },
    {
      "key": "tapmenu",
      "repo": "local/tapmenu",
      "priority": 6,
      "high_priority_lane": false,
      "repo_metrics_72h": {
        "failure_count": 0,
        "completed_count": 0
      },
      "task": {
        "created": true,
        "id": "5f37dcc3-d10e-4dd9-a7d5-47b3d50e24c7",
        "type": "opencode_controller",
        "priority": 6,
        "idempotencyKey": "opencode_controller:55e038860879031aa3125064248c0dad0dd7cae8f79dc5faae9676ee8a6b8d97"
      }
    },
    {
      "key": "trademarkhelper",
      "repo": "local/TrademarkHelper",
      "priority": 6,
      "high_priority_lane": false,
      "repo_metrics_72h": {
        "failure_count": 0,
        "completed_count": 0
      },
      "task": {
        "created": true,
        "id": "dd769c0a-dd96-4ef6-b850-faeb0e0c5ca3",
        "type": "opencode_controller",
        "priority": 6,
        "idempotencyKey": "opencode_controller:2df56772e52f3e42960ee3b65537385ae4d50ebdc2961ad6a630aa7014310abc"
      }
    },
    {
      "key": "usipeorg",
      "repo": "local/usipeorg",
      "priority": 6,
      "high_priority_lane": false,
      "repo_metrics_72h": {
        "failure_count": 0,
        "completed_count": 0
      },
      "task": {
        "created": true,
        "id": "226f8d72-5a10-4c50-8ff7-5400ed1312f5",
        "type": "opencode_controller",
        "priority": 6,
        "idempotencyKey": "opencode_controller:16b9d1d53edc021bc50f1bfb7d664a1ac69a07e304eb125d3a6ad6d43de9b1ad"
      }
    },
    {
      "key": "usipeorg",
      "repo": "local/USIPEorg",
      "priority": 6,
      "high_priority_lane": false,
      "repo_metrics_72h": {
        "failure_count": 0,
        "completed_count": 0
      },
      "task": {
        "created": true,
        "id": "ae380ea0-dd99-4e25-9714-d7e05b35dcb5",
        "type": "opencode_controller",
        "priority": 6,
        "idempotencyKey": "opencode_controller:5c4dcac65f36ba8392ed99fd8abd2eacc65c1ed970fc2b0f157aa82fe13b5a77"
      }
    },
    {
      "key": "uspto_trademark_analyzer",
      "repo": "local/uspto-trademark-analyzer",
      "priority": 6,
      "high_priority_lane": false,
      "repo_metrics_72h": {
        "failure_count": 0,
        "completed_count": 0
      },
      "task": {
        "created": true,
        "id": "8ec4d4cd-7300-4bf5-8ba5-55b0a8342e98",
        "type": "opencode_controller",
        "priority": 6,
        "idempotencyKey": "opencode_controller:2295660bc238ddb1e04677800ca2bc2dade50bf979c047a2f6434f3546b9e336"
      }
    },
    {
      "key": "v0_skyn_patch",
      "repo": "local/v0-skyn-patch",
      "priority": 6,
      "high_priority_lane": false,
      "repo_metrics_72h": {
        "failure_count": 0,
        "completed_count": 0
      },
      "task": {
        "created": true,
        "id": "30d32328-5a88-41ce-be89-85c75aa4a640",
        "type": "opencode_controller",
        "priority": 6,
        "idempotencyKey": "opencode_controller:3993fccb751e696a9114b56c8c1d2112d67f3bf7bcc8c91c37eeb74d593b317b"
      }
    },
    {
      "key": "v0_untitled_project",
      "repo": "local/v0-untitled-project",
      "priority": 6,
      "high_priority_lane": false,
      "repo_metrics_72h": {
        "failure_count": 0,
        "completed_count": 0
      },
      "task": {
        "created": true,
        "id": "d320b1e2-ce0d-4442-8c14-63da9c0c80cc",
        "type": "opencode_controller",
        "priority": 6,
        "idempotencyKey": "opencode_controller:44d145947ce7bf15203e86d69443c41d0ee916a7dc8acb272648169f5c79a9e8"
      }
    },
    {
      "key": "veritap_2026",
      "repo": "local/veritap_2026",
      "priority": 6,
      "high_priority_lane": false,
      "repo_metrics_72h": {
        "failure_count": 0,
        "completed_count": 0
      },
      "task": {
        "created": true,
        "id": "cd8e200b-2ba5-422c-babd-5edd585b3718",
        "type": "opencode_controller",
        "priority": 6,
        "idempotencyKey": "opencode_controller:8791f38cfc171a4db9a21f05fca37fb0922f24d2a39c3d765c3906fbfa1f9bb2"
      }
    },
    {
      "key": "veritap_chat",
      "repo": "local/Veritap_chat",
      "priority": 6,
      "high_priority_lane": false,
      "repo_metrics_72h": {
        "failure_count": 0,
        "completed_count": 0
      },
      "task": {
        "created": true,
        "id": "37254131-5743-4d19-8cbe-c4e5bdd8f846",
        "type": "opencode_controller",
        "priority": 6,
        "idempotencyKey": "opencode_controller:4e7d964ea059c3386c45b64f17461c4513ff85d697d2247741fddca173501b41"
      }
    },
    {
      "key": "veritapco_archive",
      "repo": "local/VeriTapco_archive",
      "priority": 6,
      "high_priority_lane": false,
      "repo_metrics_72h": {
        "failure_count": 0,
        "completed_count": 0
      },
      "task": {
        "created": true,
        "id": "a5eff1f3-30ed-47dd-8ecf-9f85e7d7ab76",
        "type": "opencode_controller",
        "priority": 6,
        "idempotencyKey": "opencode_controller:6244b2e5b419e71288b2ea1797e152d4d115ebd2d16c7d0532c8a59a89bf95f6"
      }
    },
    {
      "key": "wmac",
      "repo": "local/wmac",
      "priority": 6,
      "high_priority_lane": false,
      "repo_metrics_72h": {
        "failure_count": 0,
        "completed_count": 0
      },
      "task": {
        "created": true,
        "id": "2ee0ada0-86b7-4e37-bc43-aa5d1a21e6ed",
        "type": "opencode_controller",
        "priority": 6,
        "idempotencyKey": "opencode_controller:171b2cee5ced5a20697c4c62eb6f667c92d29cf4df0074cd4dc0fd13f2566aab"
      }
    },
    {
      "key": "wmactealth",
      "repo": "local/wmactealth",
      "priority": 6,
      "high_priority_lane": false,
      "repo_metrics_72h": {
        "failure_count": 0,
        "completed_count": 0
      },
      "task": {
        "created": true,
        "id": "9fcca182-0b81-4a8e-95c9-353d9e9acac1",
        "type": "opencode_controller",
        "priority": 6,
        "idempotencyKey": "opencode_controller:8d204026d98258f1c1d6f5d4f2a436e167fd5fe2efaa08dffcb77ee87635313e"
      }
    },
    {
      "key": "wmactealth_lc",
      "repo": "local/wmactealth-lc",
      "priority": 6,
      "high_priority_lane": false,
      "repo_metrics_72h": {
        "failure_count": 0,
        "completed_count": 0
      },
      "task": {
        "created": true,
        "id": "a5ece38a-b3c9-41fc-9829-b2f61d489950",
        "type": "opencode_controller",
        "priority": 6,
        "idempotencyKey": "opencode_controller:eee7f8397dd44b538f09de62fbaea60247892446d5d84db1c7f1ec22884412e9"
      }
    }
  ],
  "created_count": 53,
  "skipped_duplicates": 12
}